subprocess_pipe/LICENSE
subprocess_pipe/README.MD
subprocess_pipe/__init__.py
subprocess_pipe/requirements.txt
subprocess_pipe/thirdparty.json
subprocess_pipe-0.10.dist-info/LICENSE.rst
subprocess_pipe-0.10.dist-info/METADATA
subprocess_pipe-0.10.dist-info/WHEEL
subprocess_pipe-0.10.dist-info/top_level.txt
subprocess_pipe-0.10.dist-info/RECORD
